pychnosz-1.2.0.dist-info/RECORD
pychnosz-1.2.0.dist-info/WHEEL
pychnosz-1.2.0.dist-info/top_level.txt
pychnosz-1.2.0.dist-info/METADATA
pychnosz-1.2.0.dist-info/licenses/LICENSE.txt
pychnosz/_version.py
pychnosz/__init__.py
pychnosz/core/basis.py
pychnosz/core/equilibrium.py
pychnosz/core/species.py
pychnosz/core/diagram.py
pychnosz/core/equilibrate.py
pychnosz/core/subcrt.py
pychnosz/core/affinity.py
pychnosz/core/__init__.py
pychnosz/core/animation.py
pychnosz/core/thermo.py
pychnosz/core/retrieve.py
pychnosz/core/unicurve.py
pychnosz/core/info.py
pychnosz/core/speciation.py
pychnosz/core/balance.py
pychnosz/utils/units.py
pychnosz/utils/formula.py
pychnosz/utils/formula_ox.py
pychnosz/utils/reset.py
pychnosz/utils/__init__.py
pychnosz/utils/expression.py
pychnosz/models/archer_wang.py
pychnosz/models/berman.py
pychnosz/models/water.py
pychnosz/models/cgl.py
pychnosz/models/__init__.py
pychnosz/models/hkf_helpers.py
pychnosz/models/hkf.py
pychnosz/models/iapws95.py
pychnosz/models/supcrt92_fortran.py
pychnosz/models/dew.py
pychnosz/.dylibs/libgfortran.5.dylib
pychnosz/.dylibs/libquadmath.0.dylib
pychnosz/.dylibs/libgcc_s.1.1.dylib
pychnosz/fortran/h2o92_interface.py
pychnosz/fortran/__init__.py
pychnosz/fortran/.gitignore
pychnosz/fortran/h2o92.dylib
pychnosz/biomolecules/proteins.py
pychnosz/biomolecules/__init__.py
pychnosz/biomolecules/ionize_aa.py
pychnosz/data/obigt.py
pychnosz/data/worm.py
pychnosz/data/add_obigt.py
pychnosz/data/__init__.py
pychnosz/data/loader.py
pychnosz/data/mod_obigt.py
pychnosz/data/extdata/misc/bluered.txt
pychnosz/data/extdata/misc/Mer75_Table4.csv
pychnosz/data/extdata/misc/RH95.csv
pychnosz/data/extdata/misc/SS98_Fig5a.csv
pychnosz/data/extdata/misc/TKSS14_Fig2.csv
pychnosz/data/extdata/misc/PM90.csv
pychnosz/data/extdata/misc/SS98_Fig5b.csv
pychnosz/data/extdata/misc/AD03_Fig1d.csv
pychnosz/data/extdata/misc/OBIGT_check.csv
pychnosz/data/extdata/misc/AD03_Fig1a.csv
pychnosz/data/extdata/misc/AD03_Fig1b.csv
pychnosz/data/extdata/misc/AD03_Fig1c.csv
pychnosz/data/extdata/misc/SC10_Rainbow.csv
pychnosz/data/extdata/misc/BZA10.csv
