Metadata-Version: 2.4
Name: pychnosz
Version: 1.2.0
Summary: Python port of the package CHNOSZ
Author-email: Grayson Boyer <gmboyer@asu.edu>
Maintainer-email: Grayson Boyer <gmboyer@asu.edu>
License: MIT License
Project-URL: Homepage, https://worm-portal.asu.edu
Project-URL: Repository, https://github.com/worm-portal/pychnosz
Project-URL: Documentation, https://worm-portal.asu.edu/pyCHNOSZ-docs/index.html
Project-URL: Issues, https://github.com/worm-portal/pychnosz/issues
Keywords: thermodynamics,geochemistry,geobiochemistry,aqueous chemistry,equilibrium,phase diagrams
Classifier: Development Status :: 5 - Production/Stable
Classifier: Intended Audience :: Science/Research
Classifier: License :: OSI Approved :: MIT License
Classifier: Operating System :: OS Independent
Classifier: Programming Language :: Python :: 3
Classifier: Programming Language :: Python :: 3.8
Classifier: Programming Language :: Python :: 3.9
Classifier: Programming Language :: Python :: 3.10
Classifier: Programming Language :: Python :: 3.11
Classifier: Programming Language :: Python :: 3.12
Classifier: Programming Language :: Python :: 3.13
Classifier: Programming Language :: Python :: 3.14
Classifier: Topic :: Scientific/Engineering :: Chemistry
Classifier: Topic :: Scientific/Engineering :: Physics
Requires-Python: >=3.10
License-File: LICENSE.txt
Requires-Dist: numpy>=1.20.0
Requires-Dist: pandas>=1.3.0
Requires-Dist: scipy>=1.7.0
Requires-Dist: matplotlib>=3.3.0
Provides-Extra: dev
Requires-Dist: pytest>=6.0; extra == "dev"
Requires-Dist: pytest-cov; extra == "dev"
Requires-Dist: black; extra == "dev"
Requires-Dist: flake8; extra == "dev"
Requires-Dist: mypy; extra == "dev"
Requires-Dist: pre-commit; extra == "dev"
Provides-Extra: docs
Requires-Dist: sphinx>=4.0; extra == "docs"
Requires-Dist: sphinx-rtd-theme; extra == "docs"
Requires-Dist: sphinx-autodoc-typehints; extra == "docs"
Requires-Dist: myst-parser; extra == "docs"
Provides-Extra: interactive
Requires-Dist: plotly>=5.0.0; extra == "interactive"
Requires-Dist: ipython>=7.0.0; extra == "interactive"
Dynamic: license-file
